neurosound/__init__.py
neurosound/cli.py
neurosound/core.py
neurosound/py.typed
neurosound/universal.py
neurosound-3.2.0.dist-info/licenses/LICENSE
neurosound-3.2.0.dist-info/METADATA
neurosound-3.2.0.dist-info/WHEEL
neurosound-3.2.0.dist-info/entry_points.txt
neurosound-3.2.0.dist-info/top_level.txt
neurosound-3.2.0.dist-info/RECORD
