Metadata-Version: 2.4
Name: neurosound
Version: 3.2.0
Summary: Ultra-efficient audio compression: 80x ratio, multi-format support, 4 original innovations
Author-email: bhanquier <your.email@example.com>
License: MIT
Project-URL: Homepage, https://github.com/bhanquier/neuroSound
Project-URL: Documentation, https://github.com/bhanquier/neuroSound/blob/main/README.md
Project-URL: Repository, https://github.com/bhanquier/neuroSound
Project-URL: Issues, https://github.com/bhanquier/neuroSound/issues
Keywords: audio,compression,mp3,energy-efficient,spectral-analysis,green-ai
Classifier: Development Status :: 4 - Beta
Classifier: Intended Audience :: Developers
Classifier: Intended Audience :: Science/Research
Classifier: License :: OSI Approved :: MIT License
Classifier: Programming Language :: Python :: 3
Classifier: Programming Language :: Python :: 3.8
Classifier: Programming Language :: Python :: 3.9
Classifier: Programming Language :: Python :: 3.10
Classifier: Programming Language :: Python :: 3.11
Classifier: Programming Language :: Python :: 3.12
Classifier: Topic :: Multimedia :: Sound/Audio
Classifier: Topic :: Scientific/Engineering :: Artificial Intelligence
Requires-Python: >=3.8
License-File: LICENSE
Requires-Dist: numpy>=1.20.0
Provides-Extra: dev
Requires-Dist: pytest>=7.0; extra == "dev"
Requires-Dist: black>=22.0; extra == "dev"
Requires-Dist: flake8>=4.0; extra == "dev"
Dynamic: license-file
